CodeWiz/AiTool.py
CodeWiz/WizData.py
CodeWiz/WizDefaultSensor.py
CodeWiz/WizHelper.py
CodeWiz/WizSerial.py
CodeWiz/WizWrapper.py
CodeWiz/__init__.py
CodeWiz-1.0.0.dist-info/METADATA
CodeWiz-1.0.0.dist-info/WHEEL
CodeWiz-1.0.0.dist-info/top_level.txt
CodeWiz-1.0.0.dist-info/RECORD
