Metadata-Version: 2.1
Name: CodeWiz
Version: 1.0.0
Summary: Communicate with CodeWiz through Python
Home-page: https://codable.co.kr/
Author: CODABLE
Author-email: izumi@codable.co.kr
License: UNKNOWN
Platform: UNKNOWN
Classifier: Programming Language :: Python :: 3
Classifier: License :: OSI Approved :: MIT License
Classifier: Operating System :: OS Independent
Requires-Python: >=3.6
